{
	"Categories": [{
			"name": "Abstract"
		},
		{
			"name": "Aqua"
		},
		{
			"name": "Cars and Bikes"
		},
		{
			"name": "Cities"
		},
		{
			"name": "Dark Wallpapers"
		},
		{
			"name": "Dream Your Fantasy"
		},
		{
			"name": "flowers"
		},
		{
			"name": "Landscapes"
		},
		{
			"name": "Nature"
		},
		{
			"name": "Popular Wallpapers"
		},
		{
			"name": "Quotes"
		},
		{
			"name": "Roads"
		},
		{
			"name": "Sky"
		},
		{
			"name": "Textures"
		},
		{
			"name": "Ultrawide Wallpapers"
		}
	],

	"Wallpapers": [{
			"author": "Smacky™",
			"url": "https://drive.google.com/uc?id=1AMMN3bSKq29FgQPAVdoxJC5Dc16F5F23",
			"thumbUrl": "https://drive.google.com/uc?id=1AMMN3bSKq29FgQPAVdoxJC5Dc16F5F23",
			"name": "Burn Music",
			"category": "Abstract"
		},
		{
			"author": "Smacky™",
			"url": "https://drive.google.com/uc?id=1mudF4nTJ_Vu9ce8pn59N3INPGHLeuzVQ",
			"thumbUrl": "https://drive.google.com/uc?id=1mudF4nTJ_Vu9ce8pn59N3INPGHLeuzVQ",
			"name": "Color Splash",
			"category": "Abstract"
		},
		{
			"author": "Smacky™",
			"url": "https://drive.google.com/uc?id=1brHd9dHpIOo3A-ut5XfvIIlPhvleITk2",
			"thumbUrl": "https://drive.google.com/uc?id=1brHd9dHpIOo3A-ut5XfvIIlPhvleITk2",
			"name": "Water Drops",
			"category": "Abstract"
		},
		{
			"author": "Smacky™",
			"url": "https://drive.google.com/uc?id=1rKUK_I802yW1T2pZSUtz9pb-Zkxccx7v",
			"thumbUrl": "https://drive.google.com/uc?id=1rKUK_I802yW1T2pZSUtz9pb-Zkxccx7v",
			"name": "Hot air baloon",
			"category": "Abstract"
		},
		{
			"author": "Smacky™",
			"url": "https://drive.google.com/uc?id=1ftDUdAakUUzVe2AAaDO4l1bkp6BvJAdG",
			"thumbUrl": "https://drive.google.com/uc?id=1ftDUdAakUUzVe2AAaDO4l1bkp6BvJAdG",
			"name": "Day view ",
			"category": "Abstract"
		},
		{
			"author": "Smacky™",
			"url": "https://drive.google.com/uc?id=1LHD_v8ONXeyoVGxeDUwoS7r9yZFL6QQM",
			"thumbUrl": "https://drive.google.com/uc?id=1LHD_v8ONXeyoVGxeDUwoS7r9yZFL6QQM",
			"name": "Abstract Lines",
			"category": "Abstract"
		},
		{
			"author": "Smacky™",
			"url": "https://drive.google.com/uc?id=1ttEgbIknln1akmHRHhSDcoE1Yb6ZcmW5",
			"thumbUrl": "https://drive.google.com/uc?id=1ttEgbIknln1akmHRHhSDcoE1Yb6ZcmW5",
			"name": "Smoke skulls",
			"category": "Abstract"
		},
		{
			"author": "Smacky™",
			"url": "https://drive.google.com/uc?id=1nOCen-2kLJp9VIkkquxgCbRDgZy3McNl",
			"thumbUrl": "https://drive.google.com/uc?id=1nOCen-2kLJp9VIkkquxgCbRDgZy3McNl",
			"name": "Abstract View",
			"category": "Abstract"
		},
		{
			"author": "Smacky™",
			"url": "https://drive.google.com/uc?id=1bEvWYzSwwhxGaIL_puIyLwmV4HS6iZbH",
			"thumbUrl": "https://drive.google.com/uc?id=1bEvWYzSwwhxGaIL_puIyLwmV4HS6iZbH",
			"name": "Water Drops",
			"category": "Abstract"
		},
		{
			"author": "Smacky™",
			"url": "https://drive.google.com/uc?id=1D5f3_tMyVyKzLkaJ5wHhaZKKUiIkysg7",
			"thumbUrl": "https://drive.google.com/uc?id=1D5f3_tMyVyKzLkaJ5wHhaZKKUiIkysg7",
			"name": "Dark Pattern",
			"category": "Abstract"
		},
		{
			"author": "Smacky™",
			"url": "https://drive.google.com/uc?id=1PKmbvack0sYS38_chuwQuFF_DFY7Z_Y-",
			"thumbUrl": "https://drive.google.com/uc?id=1PKmbvack0sYS38_chuwQuFF_DFY7Z_Y-",
			"name": "Random Letters",
			"category": "Abstract"
		},
		{
			"author": "Smacky™",
			"url": "https://drive.google.com/uc?id=12-Ufop2s4n9Mk5hhnLNW3Y6iM5n91V3R",
			"thumbUrl": "https://drive.google.com/uc?id=12-Ufop2s4n9Mk5hhnLNW3Y6iM5n91V3R",
			"name": "Abstract Glass",
			"category": "Abstract"
		},
		{
			"author": "Smacky™",
			"url": "https://drive.google.com/uc?id=1C9ILjZPSsw3aBc-uA6c8KkffyKPZtWuc",
			"thumbUrl": "https://drive.google.com/uc?id=1C9ILjZPSsw3aBc-uA6c8KkffyKPZtWuc",
			"name": "Skyscraper",
			"category": "Abstract"
		},
		{
			"author": "Smacky™",
			"url": "https://drive.google.com/uc?id=1VbzRk32H0O-9v0VFtho_4WkIbNMYz5Bt",
			"thumbUrl": "https://drive.google.com/uc?id=1VbzRk32H0O-9v0VFtho_4WkIbNMYz5Bt",
			"name": "Colored View",
			"category": "Abstract"
		},
		{
			"author": "Smacky™",
			"url": "https://drive.google.com/uc?id=13cGJIO8hr6XoLM-NrgCEYNZvtkRqhnvH",
			"thumbUrl": "https://drive.google.com/uc?id=13cGJIO8hr6XoLM-NrgCEYNZvtkRqhnvH",
			"name": "Ice Fall",
			"category": "Abstract"
		},
		{
			"author": "Smacky™",
			"url": "https://drive.google.com/uc?id=1Rw03reIlnnoGiMJTBnCg8R1QaDzecAim",
			"thumbUrl": "https://drive.google.com/uc?id=1Rw03reIlnnoGiMJTBnCg8R1QaDzecAim",
			"name": "Dark Shark",
			"category": "Abstract"
		},
		{
			"author": "Smacky™",
			"url": "https://drive.google.com/uc?id=1Y3RhDJiu6TcOnJDP1B5HVyLbeSC35eSz",
			"thumbUrl": "https://drive.google.com/uc?id=1Y3RhDJiu6TcOnJDP1B5HVyLbeSC35eSz",
			"name": "Anim. tree",
			"category": "Abstract"
		},
		{
			"author": "Smacky™",
			"url": "https://drive.google.com/uc?id=17kqRJOqXrQAloGsXKT6lXLSKZe4Mxkf8",
			"thumbUrl": "https://drive.google.com/uc?id=17kqRJOqXrQAloGsXKT6lXLSKZe4Mxkf8",
			"name": "Glass floor",
			"category": "Abstract"
		},
		{
			"author": "Smacky™",
			"url": "https://drive.google.com/uc?id=1n8WJRzN5PO1ogxf53xl6EVFXth5nAkz8",
			"thumbUrl": "https://drive.google.com/uc?id=1n8WJRzN5PO1ogxf53xl6EVFXth5nAkz8",
			"name": "Abstract Line",
			"category": "Abstract"
		},
		{
			"author": "Smacky™",
			"url": "https://drive.google.com/uc?id=1-s0GpCce4MUE9BKWDkF0LuHo9wqAo1ro",
			"thumbUrl": "https://drive.google.com/uc?id=1-s0GpCce4MUE9BKWDkF0LuHo9wqAo1ro",
			"name": "Confuse Lines",
			"category": "Abstract"
		},
		{
			"author": "Smacky™",
			"url": "https://drive.google.com/uc?id=15T3-xzbEijE0y6T1Jomvw3dXGFCIrQH2",
			"thumbUrl": "https://drive.google.com/uc?id=15T3-xzbEijE0y6T1Jomvw3dXGFCIrQH2",
			"name": "Diamond Star",
			"category": "Abstract"
		},
		{
			"author": "Smacky™",
			"url": "https://drive.google.com/uc?id=1CN9OCea-Fwtq0cw4ZyJE1m-eGC3elbjL",
			"thumbUrl": "https://drive.google.com/uc?id=1CN9OCea-Fwtq0cw4ZyJE1m-eGC3elbjL",
			"name": "Pixel of Lights",
			"category": "Abstract"
		},
		{
			"author": "Smacky™",
			"url": "https://drive.google.com/uc?id=1XdYyMyC_PGoHgwvjW1HCoXqPnjnEz7Pp",
			"thumbUrl": "https://drive.google.com/uc?id=1XdYyMyC_PGoHgwvjW1HCoXqPnjnEz7Pp",
			"name": "Stones",
			"category": "Abstract"
		},
		{
			"author": "Smacky™",
			"url": "https://drive.google.com/uc?id=1Z1hHY_5i9xCHumtC1ygWOuRww30DlBeP",
			"thumbUrl": "https://drive.google.com/uc?id=1Z1hHY_5i9xCHumtC1ygWOuRww30DlBeP",
			"name": "Abstract Diamond",
			"category": "Abstract"
		},
		{
			"author": "Smacky™",
			"url": "https://drive.google.com/uc?id=1_DJK0YAYF_68aiMxJXZ3sGlMKC2kJDLP",
			"thumbUrl": "https://drive.google.com/uc?id=1_DJK0YAYF_68aiMxJXZ3sGlMKC2kJDLP",
			"name": "Colorfull View ",
			"category": "Abstract"
		},
		{
			"author": "Smacky™",
			"url": "https://drive.google.com/uc?id=1luXwpMTxJsJ2z_gjMbodyi_9MyRzdOSV",
			"thumbUrl": "https://drive.google.com/uc?id=1luXwpMTxJsJ2z_gjMbodyi_9MyRzdOSV",
			"name": "3d Lines",
			"category": "Abstract"
		},
		








		{
			"author": "Smacky™",
			"url": "https://drive.google.com/open?id=11wQJrOulKLQfJ9_Bz7LT03Yb5UtYocQn",
			"thumbUrl": "https://drive.google.com/open?id=11wQJrOulKLQfJ9_Bz7LT03Yb5UtYocQn",
			"name": "Sea Wave",
			"category": "Aqua"
		},
		{
			"author": "Smacky™",
			"url": "https://drive.google.com/open?id=1fPuRairtCqbplAC4r-hUUZ8NLt5I1naZ",
			"thumbUrl": "https://drive.google.com/open?id=1fPuRairtCqbplAC4r-hUUZ8NLt5I1naZ",
			"name": "A view from glass",
			"category": "Aqua"
		},
		{
			"author": "Smacky™",
			"url": "https://drive.google.com/open?id=1-HAXgwPesMfMmkC9-XUO6UF6hGy2XZlH",
			"thumbUrl": "https://drive.google.com/open?id=1-HAXgwPesMfMmkC9-XUO6UF6hGy2XZlH",
			"name": "Gold fish",
			"category": "Aqua"
		},
		{
			"author": "Smacky™",
			"url": "https://drive.google.com/open?id=1T0Wq7jGxX66WfTJWiMizJK7JOxwUxWgc",
			"thumbUrl": "https://drive.google.com/open?id=1T0Wq7jGxX66WfTJWiMizJK7JOxwUxWgc",
			"name": "Gold fish",
			"category": "Aqua"
		},
		{
			"author": "Smacky™",
			"url": "https://drive.google.com/open?id=1s_62pL8_I0cKygYqYzzr4HiBPumNhBjy",
			"thumbUrl": "https://drive.google.com/open?id=1s_62pL8_I0cKygYqYzzr4HiBPumNhBjy",
			"name": "Marine Things",
			"category": "Aqua"
		},
		{
			"author": "Smacky™",
			"url": "https://drive.google.com/open?id=1BE3egarx9ZJRnOP8aKZBRbTO1WkPuug1",
			"thumbUrl": "https://drive.google.com/open?id=1BE3egarx9ZJRnOP8aKZBRbTO1WkPuug1",
			"name": "A little aquarium",
			"category": "Aqua"
		},








		{
			"author": "Smacky™",
			"url": "  ",
			"thumbUrl": "  ",
			"name": "         ",

			"category": "Cars and Bikes"
		},
		{
			"author": "Smacky™",
			"url": "  ",
			"thumbUrl": "  ",
			"name": "         ",

			"category": "Cars and Bikes"
		},
		{
			"author": "Smacky™",
			"url": "  ",
			"thumbUrl": "  ",
			"name": "         ",

			"category": "Cars and Bikes"
		},
		{
			"author": "Smacky™",
			"url": "  ",
			"thumbUrl": "  ",
			"name": "         ",

			"category": "Cars and Bikes"
		},
		{
			"author": "Smacky™",
			"url": "  ",
			"thumbUrl": "  ",
			"name": "         ",

			"category": "Cars and Bikes"
		},
		{
			"author": "Smacky™",
			"url": "  ",
			"thumbUrl": "  ",
			"name": "         ",

			"category": "Cars and Bikes"
		},
		{
			"author": "Smacky™",
			"url": "  ",
			"thumbUrl": "  ",
			"name": "         ",

			"category": "Cars and Bikes"
		},
		{
			"author": "Smacky™",
			"url": "  ",
			"thumbUrl": "  ",
			"name": "         ",

			"category": "Cars and Bikes"
		},
		{
			"author": "Smacky™",
			"url": "  ",
			"thumbUrl": "  ",
			"name": "         ",

			"category": "Cars and Bikes"
		},
		{
			"author": "Smacky™",
			"url": "  ",
			"thumbUrl": "  ",
			"name": "         ",

			"category": "Cars and Bikes"
		},
		{
			"author": "Smacky™",
			"url": "  ",
			"thumbUrl": "  ",
			"name": "         ",

			"category": "Cars and Bikes"
		},
		{
			"author": "Smacky™",
			"url": "  ",
			"thumbUrl": "  ",
			"name": "         ",

			"category": "Cars and Bikes"
		},
		{
			"author": "Smacky™",
			"url": "  ",
			"thumbUrl": "  ",
			"name": "         ",

			"category": "Cars and Bikes"
		},
		{
			"author": "Smacky™",
			"url": "  ",
			"thumbUrl": "  ",
			"name": "         ",

			"category": "Cars and Bikes"
		},
		{
			"author": "Smacky™",
			"url": "  ",
			"thumbUrl": "  ",
			"name": "         ",

			"category": "Cars and Bikes"
		},
		{
			"author": "Smacky™",
			"url": "  ",
			"thumbUrl": "  ",
			"name": "         ",

			"category": "Cars and Bikes"
		},
		{
			"author": "Smacky™",
			"url": "  ",
			"thumbUrl": "  ",
			"name": "         ",

			"category": "Cars and Bikes"
		},
		{
			"author": "Smacky™",
			"url": "  ",
			"thumbUrl": "  ",
			"name": "         ",

			"category": "Cars and Bikes"
		},
		{
			"author": "Smacky™",
			"url": "  ",
			"thumbUrl": "  ",
			"name": "         ",

			"category": "Cars and Bikes"
		},
		{
			"author": "Smacky™",
			"url": "  ",
			"thumbUrl": "  ",
			"name": "         ",

			"category": "Cars and Bikes"
		},









		{
			"author": "Smacky™",
			"url": "  ",
			"thumbUrl": "  ",
			"name": "         ",

			"category": "Cities"
		},
		{
			"author": "Smacky™",
			"url": "  ",
			"thumbUrl": "  ",
			"name": "         ",

			"category": "Cities"
		},
		{
			"author": "Smacky™",
			"url": "  ",
			"thumbUrl": "  ",
			"name": "         ",

			"category": "Cities"
		},
		{
			"author": "Smacky™",
			"url": "  ",
			"thumbUrl": "  ",
			"name": "         ",

			"category": "Cities"
		},
		{
			"author": "Smacky™",
			"url": "  ",
			"thumbUrl": "  ",
			"name": "         ",

			"category": "Cities"
		},
		{
			"author": "Smacky™",
			"url": "  ",
			"thumbUrl": "  ",
			"name": "         ",

			"category": "Cities"
		},
		{
			"author": "Smacky™",
			"url": "  ",
			"thumbUrl": "  ",
			"name": "         ",

			"category": "Cities"
		},
		{
			"author": "Smacky™",
			"url": "  ",
			"thumbUrl": "  ",
			"name": "         ",

			"category": "Cities"
		},
		{
			"author": "Smacky™",
			"url": "  ",
			"thumbUrl": "  ",
			"name": "         ",

			"category": "Cities"
		},
		{
			"author": "Smacky™",
			"url": "  ",
			"thumbUrl": "  ",
			"name": "         ",

			"category": "Cities"
		},
		{
			"author": "Smacky™",
			"url": "  ",
			"thumbUrl": "  ",
			"name": "         ",

			"category": "Cities"
		},
		{
			"author": "Smacky™",
			"url": "  ",
			"thumbUrl": "  ",
			"name": "         ",

			"category": "Cities"
		},
		{
			"author": "Smacky™",
			"url": "  ",
			"thumbUrl": "  ",
			"name": "         ",

			"category": "Cities"
		},
		{
			"author": "Smacky™",
			"url": "  ",
			"thumbUrl": "  ",
			"name": "         ",

			"category": "Cities"
		},
		{
			"author": "Smacky™",
			"url": "  ",
			"thumbUrl": "  ",
			"name": "         ",

			"category": "Cities"
		},
		{
			"author": "Smacky™",
			"url": "  ",
			"thumbUrl": "  ",
			"name": "         ",

			"category": "Cities"
		},
		{
			"author": "Smacky™",
			"url": "  ",
			"thumbUrl": "  ",
			"name": "         ",

			"category": "Cities"
		},
		{
			"author": "Smacky™",
			"url": "  ",
			"thumbUrl": "  ",
			"name": "         ",

			"category": "Cities"
		},
		{
			"author": "Smacky™",
			"url": "  ",
			"thumbUrl": "  ",
			"name": "         ",

			"category": "Cities"
		},
		{
			"author": "Smacky™",
			"url": "  ",
			"thumbUrl": "  ",
			"name": "         ",

			"category": "Cities"
		},
		{
			"author": "Smacky™",
			"url": "  ",
			"thumbUrl": "  ",
			"name": "         ",

			"category": "Cities"
		},
		{
			"author": "Smacky™",
			"url": "  ",
			"thumbUrl": "  ",
			"name": "         ",

			"category": "Cities"
		},
		{
			"author": "Smacky™",
			"url": "  ",
			"thumbUrl": "  ",
			"name": "         ",

			"category": "Cities"
		},
		{
			"author": "Smacky™",
			"url": "  ",
			"thumbUrl": "  ",
			"name": "         ",

			"category": "Cities"
		},













		{
			"author": "Smacky™",
			"url": "  ",
			"thumbUrl": "  ",
			"name": "         ",

			"category": "Dark Wallpapers"
		},
		{
			"author": "Smacky™",
			"url": "  ",
			"thumbUrl": "  ",
			"name": "         ",

			"category": "Dark Wallpapers"
		},
		{
			"author": "Smacky™",
			"url": "  ",
			"thumbUrl": "  ",
			"name": "         ",

			"category": "Dark Wallpapers"
		},
		{
			"author": "Smacky™",
			"url": "  ",
			"thumbUrl": "  ",
			"name": "         ",

			"category": "Dark Wallpapers"
		},
		{
			"author": "Smacky™",
			"url": "  ",
			"thumbUrl": "  ",
			"name": "         ",

			"category": "Dark Wallpapers"
		},
		{
			"author": "Smacky™",
			"url": "  ",
			"thumbUrl": "  ",
			"name": "         ",

			"category": "Dark Wallpapers"
		},
		{
			"author": "Smacky™",
			"url": "  ",
			"thumbUrl": "  ",
			"name": "         ",

			"category": "Dark Wallpapers"
		},
		{
			"author": "Smacky™",
			"url": "  ",
			"thumbUrl": "  ",
			"name": "         ",

			"category": "Dark Wallpapers"
		},
		{
			"author": "Smacky™",
			"url": "  ",
			"thumbUrl": "  ",
			"name": "         ",

			"category": "Dark Wallpapers"
		},
		{
			"author": "Smacky™",
			"url": "  ",
			"thumbUrl": "  ",
			"name": "         ",

			"category": "Dark Wallpapers"
		},
		{
			"author": "Smacky™",
			"url": "  ",
			"thumbUrl": "  ",
			"name": "         ",

			"category": "Dark Wallpapers"
		},
		{
			"author": "Smacky™",
			"url": "  ",
			"thumbUrl": "  ",
			"name": "         ",

			"category": "Dark Wallpapers"
		},
		{
			"author": "Smacky™",
			"url": "  ",
			"thumbUrl": "  ",
			"name": "         ",

			"category": "Dark Wallpapers"
		},
		{
			"author": "Smacky™",
			"url": "  ",
			"thumbUrl": "  ",
			"name": "         ",

			"category": "Dark Wallpapers"
		},
		{
			"author": "Smacky™",
			"url": "  ",
			"thumbUrl": "  ",
			"name": "         ",

			"category": "Dark Wallpapers"
		},
		{
			"author": "Smacky™",
			"url": "  ",
			"thumbUrl": "  ",
			"name": "         ",

			"category": "Dark Wallpapers"
		},








		{
			"author": "Smacky™",
			"url": "  ",
			"thumbUrl": "  ",
			"name": "         ",

			"category": "Dream Your Fantasy"
		},
		{
			"author": "Smacky™",
			"url": "  ",
			"thumbUrl": "  ",
			"name": "         ",

			"category": "Dream Your Fantasy"
		},
		{
			"author": "Smacky™",
			"url": "  ",
			"thumbUrl": "  ",
			"name": "         ",

			"category": "Dream Your Fantasy"
		},
		{
			"author": "Smacky™",
			"url": "  ",
			"thumbUrl": "  ",
			"name": "         ",

			"category": "Dream Your Fantasy"
		},
		{
			"author": "Smacky™",
			"url": "  ",
			"thumbUrl": "  ",
			"name": "         ",

			"category": "Dream Your Fantasy"
		},
		{
			"author": "Smacky™",
			"url": "  ",
			"thumbUrl": "  ",
			"name": "         ",

			"category": "Dream Your Fantasy"
		},
		{
			"author": "Smacky™",
			"url": "  ",
			"thumbUrl": "  ",
			"name": "         ",

			"category": "Dream Your Fantasy"
		},
		{
			"author": "Smacky™",
			"url": "  ",
			"thumbUrl": "  ",
			"name": "         ",

			"category": "Dream Your Fantasy"
		},
		{
			"author": "Smacky™",
			"url": "  ",
			"thumbUrl": "  ",
			"name": "         ",

			"category": "Dream Your Fantasy"
		},
		{
			"author": "Smacky™",
			"url": "  ",
			"thumbUrl": "  ",
			"name": "         ",

			"category": "Dream Your Fantasy"
		},
		{
			"author": "Smacky™",
			"url": "  ",
			"thumbUrl": "  ",
			"name": "         ",

			"category": "Dream Your Fantasy"
		},
		{
			"author": "Smacky™",
			"url": "  ",
			"thumbUrl": "  ",
			"name": "         ",

			"category": "Dream Your Fantasy"
		},
		{
			"author": "Smacky™",
			"url": "  ",
			"thumbUrl": "  ",
			"name": "         ",

			"category": "Dream Your Fantasy"
		},
		{
			"author": "Smacky™",
			"url": "  ",
			"thumbUrl": "  ",
			"name": "         ",

			"category": "Dream Your Fantasy"
		},
		{
			"author": "Smacky™",
			"url": "  ",
			"thumbUrl": "  ",
			"name": "         ",

			"category": "Dream Your Fantasy"
		},
		{
			"author": "Smacky™",
			"url": "  ",
			"thumbUrl": "  ",
			"name": "         ",

			"category": "Dream Your Fantasy"
		},
		{
			"author": "Smacky™",
			"url": "  ",
			"thumbUrl": "  ",
			"name": "         ",

			"category": "Dream Your Fantasy"
		},
		{
			"author": "Smacky™",
			"url": "  ",
			"thumbUrl": "  ",
			"name": "         ",

			"category": "Dream Your Fantasy"
		},














		{
			"author": "Smacky™",
			"url": "  ",
			"thumbUrl": "  ",
			"name": "         ",

			"category": "flowers"
		},
		{
			"author": "Smacky™",
			"url": "  ",
			"thumbUrl": "  ",
			"name": "         ",

			"category": "flowers"
		},
		{
			"author": "Smacky™",
			"url": "  ",
			"thumbUrl": "  ",
			"name": "         ",

			"category": "flowers"
		},
		{
			"author": "Smacky™",
			"url": "  ",
			"thumbUrl": "  ",
			"name": "         ",

			"category": "flowers"
		},
		{
			"author": "Smacky™",
			"url": "  ",
			"thumbUrl": "  ",
			"name": "         ",

			"category": "flowers"
		},
		{
			"author": "Smacky™",
			"url": "  ",
			"thumbUrl": "  ",
			"name": "         ",

			"category": "flowers"
		},
		{
			"author": "Smacky™",
			"url": "  ",
			"thumbUrl": "  ",
			"name": "         ",

			"category": "flowers"
		},
		{
			"author": "Smacky™",
			"url": "  ",
			"thumbUrl": "  ",
			"name": "         ",

			"category": "flowers"
		},
		{
			"author": "Smacky™",
			"url": "  ",
			"thumbUrl": "  ",
			"name": "         ",

			"category": "flowers"
		},
		{
			"author": "Smacky™",
			"url": "  ",
			"thumbUrl": "  ",
			"name": "         ",

			"category": "flowers"
		},













		{
			"author": "Smacky™",
			"url": "  ",
			"thumbUrl": "  ",
			"name": "         ",

			"category": "Landscapes"
		},
		{
			"author": "Smacky™",
			"url": "  ",
			"thumbUrl": "  ",
			"name": "         ",

			"category": "Landscapes"
		},
		{
			"author": "Smacky™",
			"url": "  ",
			"thumbUrl": "  ",
			"name": "         ",

			"category": "Landscapes"
		},
		{
			"author": "Smacky™",
			"url": "  ",
			"thumbUrl": "  ",
			"name": "         ",

			"category": "Landscapes"
		},
		{
			"author": "Smacky™",
			"url": "  ",
			"thumbUrl": "  ",
			"name": "         ",

			"category": "Landscapes"
		},
		{
			"author": "Smacky™",
			"url": "  ",
			"thumbUrl": "  ",
			"name": "         ",

			"category": "Landscapes"
		},
		{
			"author": "Smacky™",
			"url": "  ",
			"thumbUrl": "  ",
			"name": "         ",

			"category": "Landscapes"
		},
		{
			"author": "Smacky™",
			"url": "  ",
			"thumbUrl": "  ",
			"name": "         ",

			"category": "Landscapes"
		},
		{
			"author": "Smacky™",
			"url": "  ",
			"thumbUrl": "  ",
			"name": "         ",

			"category": "Landscapes"
		},
		{
			"author": "Smacky™",
			"url": "  ",
			"thumbUrl": "  ",
			"name": "         ",

			"category": "Landscapes"
		},
		{
			"author": "Smacky™",
			"url": "  ",
			"thumbUrl": "  ",
			"name": "         ",

			"category": "Landscapes"
		},
		{
			"author": "Smacky™",
			"url": "  ",
			"thumbUrl": "  ",
			"name": "         ",

			"category": "Landscapes"
		},
		{
			"author": "Smacky™",
			"url": "  ",
			"thumbUrl": "  ",
			"name": "         ",

			"category": "Landscapes"
		},
		{
			"author": "Smacky™",
			"url": "  ",
			"thumbUrl": "  ",
			"name": "         ",

			"category": "Landscapes"
		},
		{
			"author": "Smacky™",
			"url": "  ",
			"thumbUrl": "  ",
			"name": "         ",

			"category": "Landscapes"
		},
		{
			"author": "Smacky™",
			"url": "  ",
			"thumbUrl": "  ",
			"name": "         ",

			"category": "Landscapes"
		},
		{
			"author": "Smacky™",
			"url": "  ",
			"thumbUrl": "  ",
			"name": "         ",

			"category": "Landscapes"
		},
		{
			"author": "Smacky™",
			"url": "  ",
			"thumbUrl": "  ",
			"name": "         ",

			"category": "Landscapes"
		},
		{
			"author": "Smacky™",
			"url": "  ",
			"thumbUrl": "  ",
			"name": "         ",

			"category": "Landscapes"
		},
		{
			"author": "Smacky™",
			"url": "  ",
			"thumbUrl": "  ",
			"name": "         ",

			"category": "Landscapes"
		},
		{
			"author": "Smacky™",
			"url": "  ",
			"thumbUrl": "  ",
			"name": "         ",

			"category": "Landscapes"
		},
		{
			"author": "Smacky™",
			"url": "  ",
			"thumbUrl": "  ",
			"name": "         ",

			"category": "Landscapes"
		},
		{
			"author": "Smacky™",
			"url": "  ",
			"thumbUrl": "  ",
			"name": "         ",

			"category": "Landscapes"
		},
		{
			"author": "Smacky™",
			"url": "  ",
			"thumbUrl": "  ",
			"name": "         ",

			"category": "Landscapes"
		},
		{
			"author": "Smacky™",
			"url": "  ",
			"thumbUrl": "  ",
			"name": "         ",

			"category": "Landscapes"
		},
		{
			"author": "Smacky™",
			"url": "  ",
			"thumbUrl": "  ",
			"name": "         ",

			"category": "Landscapes"
		},
		{
			"author": "Smacky™",
			"url": "  ",
			"thumbUrl": "  ",
			"name": "         ",

			"category": "Landscapes"
		},



















		{
			"author": "Smacky™",
			"url": "  ",
			"thumbUrl": "  ",
			"name": "         ",

			"category": "Nature"
		},
		{
			"author": "Smacky™",
			"url": "  ",
			"thumbUrl": "  ",
			"name": "         ",

			"category": "Nature"
		},
		{
			"author": "Smacky™",
			"url": "  ",
			"thumbUrl": "  ",
			"name": "         ",

			"category": "Nature"
		},
		{
			"author": "Smacky™",
			"url": "  ",
			"thumbUrl": "  ",
			"name": "         ",

			"category": "Nature"
		},
		{
			"author": "Smacky™",
			"url": "  ",
			"thumbUrl": "  ",
			"name": "         ",

			"category": "Nature"
		},
		{
			"author": "Smacky™",
			"url": "  ",
			"thumbUrl": "  ",
			"name": "         ",

			"category": "Nature"
		},
		{
			"author": "Smacky™",
			"url": "  ",
			"thumbUrl": "  ",
			"name": "         ",

			"category": "Nature"
		},
		{
			"author": "Smacky™",
			"url": "  ",
			"thumbUrl": "  ",
			"name": "         ",

			"category": "Nature"
		},
		{
			"author": "Smacky™",
			"url": "  ",
			"thumbUrl": "  ",
			"name": "         ",

			"category": "Nature"
		},
		{
			"author": "Smacky™",
			"url": "  ",
			"thumbUrl": "  ",
			"name": "         ",

			"category": "Nature"
		},
		{
			"author": "Smacky™",
			"url": "  ",
			"thumbUrl": "  ",
			"name": "         ",

			"category": "Nature"
		},
		{
			"author": "Smacky™",
			"url": "  ",
			"thumbUrl": "  ",
			"name": "         ",

			"category": "Nature"
		},
		{
			"author": "Smacky™",
			"url": "  ",
			"thumbUrl": "  ",
			"name": "         ",

			"category": "Nature"
		},
		{
			"author": "Smacky™",
			"url": "  ",
			"thumbUrl": "  ",
			"name": "         ",

			"category": "Nature"
		},
		{
			"author": "Smacky™",
			"url": "  ",
			"thumbUrl": "  ",
			"name": "         ",

			"category": "Nature"
		},
		{
			"author": "Smacky™",
			"url": "  ",
			"thumbUrl": "  ",
			"name": "         ",

			"category": "Nature"
		},
		{
			"author": "Smacky™",
			"url": "  ",
			"thumbUrl": "  ",
			"name": "         ",

			"category": "Nature"
		},
		{
			"author": "Smacky™",
			"url": "  ",
			"thumbUrl": "  ",
			"name": "         ",

			"category": "Nature"
		},
		{
			"author": "Smacky™",
			"url": "  ",
			"thumbUrl": "  ",
			"name": "         ",

			"category": "Nature"
		},
		{
			"author": "Smacky™",
			"url": "  ",
			"thumbUrl": "  ",
			"name": "         ",

			"category": "Nature"
		},
		{
			"author": "Smacky™",
			"url": "  ",
			"thumbUrl": "  ",
			"name": "         ",

			"category": "Nature"
		},
		{
			"author": "Smacky™",
			"url": "  ",
			"thumbUrl": "  ",
			"name": "         ",

			"category": "Nature"
		},
		{
			"author": "Smacky™",
			"url": "  ",
			"thumbUrl": "  ",
			"name": "         ",

			"category": "Nature"
		},
		{
			"author": "Smacky™",
			"url": "  ",
			"thumbUrl": "  ",
			"name": "         ",

			"category": "Nature"
		},
		{
			"author": "Smacky™",
			"url": "  ",
			"thumbUrl": "  ",
			"name": "         ",

			"category": "Nature"
		},
		{
			"author": "Smacky™",
			"url": "  ",
			"thumbUrl": "  ",
			"name": "         ",

			"category": "Nature"
		},
		{
			"author": "Smacky™",
			"url": "  ",
			"thumbUrl": "  ",
			"name": "         ",

			"category": "Nature"
		},
		{
			"author": "Smacky™",
			"url": "  ",
			"thumbUrl": "  ",
			"name": "         ",

			"category": "Nature"
		},
		{
			"author": "Smacky™",
			"url": "  ",
			"thumbUrl": "  ",
			"name": "         ",

			"category": "Nature"
		},
		{
			"author": "Smacky™",
			"url": "  ",
			"thumbUrl": "  ",
			"name": "         ",

			"category": "Nature"
		},
		{
			"author": "Smacky™",
			"url": "  ",
			"thumbUrl": "  ",
			"name": "         ",

			"category": "Nature"
		},
		{
			"author": "Smacky™",
			"url": "  ",
			"thumbUrl": "  ",
			"name": "         ",

			"category": "Nature"
		},
		{
			"author": "Smacky™",
			"url": "  ",
			"thumbUrl": "  ",
			"name": "         ",

			"category": "Nature"
		},
		{
			"author": "Smacky™",
			"url": "  ",
			"thumbUrl": "  ",
			"name": "         ",

			"category": "Nature"
		},
		{
			"author": "Smacky™",
			"url": "  ",
			"thumbUrl": "  ",
			"name": "         ",

			"category": "Nature"
		},
		{
			"author": "Smacky™",
			"url": "  ",
			"thumbUrl": "  ",
			"name": "         ",

			"category": "Nature"
		},
		{
			"author": "Smacky™",
			"url": "  ",
			"thumbUrl": "  ",
			"name": "         ",

			"category": "Nature"
		},
		{
			"author": "Smacky™",
			"url": "  ",
			"thumbUrl": "  ",
			"name": "         ",

			"category": "Nature"
		},
		{
			"author": "Smacky™",
			"url": "  ",
			"thumbUrl": "  ",
			"name": "         ",

			"category": "Nature"
		},
		{
			"author": "Smacky™",
			"url": "  ",
			"thumbUrl": "  ",
			"name": "         ",

			"category": "Nature"
		},
		{
			"author": "Smacky™",
			"url": "  ",
			"thumbUrl": "  ",
			"name": "         ",

			"category": "Nature"
		},
		{
			"author": "Smacky™",
			"url": "  ",
			"thumbUrl": "  ",
			"name": "         ",

			"category": "Nature"
		},
		{
			"author": "Smacky™",
			"url": "  ",
			"thumbUrl": "  ",
			"name": "         ",

			"category": "Nature"
		},
		{
			"author": "Smacky™",
			"url": "  ",
			"thumbUrl": "  ",
			"name": "         ",

			"category": "Nature"
		},
		{
			"author": "Smacky™",
			"url": "  ",
			"thumbUrl": "  ",
			"name": "         ",

			"category": "Nature"
		},
		{
			"author": "Smacky™",
			"url": "  ",
			"thumbUrl": "  ",
			"name": "         ",

			"category": "Nature"
		},
		{
			"author": "Smacky™",
			"url": "  ",
			"thumbUrl": "  ",
			"name": "         ",

			"category": "Nature"
		},
		{
			"author": "Smacky™",
			"url": "  ",
			"thumbUrl": "  ",
			"name": "         ",

			"category": "Nature"
		},
		{
			"author": "Smacky™",
			"url": "  ",
			"thumbUrl": "  ",
			"name": "         ",

			"category": "Nature"
		},
		{
			"author": "Smacky™",
			"url": "  ",
			"thumbUrl": "  ",
			"name": "         ",

			"category": "Nature"
		},
		{
			"author": "Smacky™",
			"url": "  ",
			"thumbUrl": "  ",
			"name": "         ",

			"category": "Nature"
		},
		{
			"author": "Smacky™",
			"url": "  ",
			"thumbUrl": "  ",
			"name": "         ",

			"category": "Nature"
		},
		{
			"author": "Smacky™",
			"url": "  ",
			"thumbUrl": "  ",
			"name": "         ",

			"category": "Nature"
		},










		{
			"author": "Smacky™",
			"url": "  ",
			"thumbUrl": "  ",
			"name": "         ",

	"category": "Popular Wallpapers"
		},

		{
			"author": "Smacky™",
			"url": "  ",
			"thumbUrl": "  ",
			"name": "         ",

	"category": "Popular Wallpapers"
		},

		{
			"author": "Smacky™",
			"url": "  ",
			"thumbUrl": "  ",
			"name": "         ",

	"category": "Popular Wallpapers"
		},

		{
			"author": "Smacky™",
			"url": "  ",
			"thumbUrl": "  ",
			"name": "         ",

	"category": "Popular Wallpapers"
		},

		{
			"author": "Smacky™",
			"url": "  ",
			"thumbUrl": "  ",
			"name": "         ",

	"category": "Popular Wallpapers"
		},

		{
			"author": "Smacky™",
			"url": "  ",
			"thumbUrl": "  ",
			"name": "         ",

	"category": "Popular Wallpapers"
		},

		{
			"author": "Smacky™",
			"url": "  ",
			"thumbUrl": "  ",
			"name": "         ",

	"category": "Popular Wallpapers"
		},

		{
			"author": "Smacky™",
			"url": "  ",
			"thumbUrl": "  ",
			"name": "         ",

	"category": "Popular Wallpapers"
		},

		{
			"author": "Smacky™",
			"url": "  ",
			"thumbUrl": "  ",
			"name": "         ",

	"category": "Popular Wallpapers"
		},

		{
			"author": "Smacky™",
			"url": "  ",
			"thumbUrl": "  ",
			"name": "         ",

	"category": "Popular Wallpapers"
		},

		{
			"author": "Smacky™",
			"url": "  ",
			"thumbUrl": "  ",
			"name": "         ",

	"category": "Popular Wallpapers"
		},

		{
			"author": "Smacky™",
			"url": "  ",
			"thumbUrl": "  ",
			"name": "         ",

	"category": "Popular Wallpapers"
		},

		{
			"author": "Smacky™",
			"url": "  ",
			"thumbUrl": "  ",
			"name": "         ",

	"category": "Popular Wallpapers"
		},

		{
			"author": "Smacky™",
			"url": "  ",
			"thumbUrl": "  ",
			"name": "         ",

	"category": "Popular Wallpapers"
		},

		{
			"author": "Smacky™",
			"url": "  ",
			"thumbUrl": "  ",
			"name": "         ",

	"category": "Popular Wallpapers"
		},

		{
			"author": "Smacky™",
			"url": "  ",
			"thumbUrl": "  ",
			"name": "         ",

	"category": "Popular Wallpapers"
		},

		{
			"author": "Smacky™",
			"url": "  ",
			"thumbUrl": "  ",
			"name": "         ",

	"category": "Popular Wallpapers"
		},

		{
			"author": "Smacky™",
			"url": "  ",
			"thumbUrl": "  ",
			"name": "         ",

	"category": "Popular Wallpapers"
		},

		{
			"author": "Smacky™",
			"url": "  ",
			"thumbUrl": "  ",
			"name": "         ",

	"category": "Popular Wallpapers"
		},

		{
			"author": "Smacky™",
			"url": "  ",
			"thumbUrl": "  ",
			"name": "         ",

	"category": "Popular Wallpapers"
		},

		{
			"author": "Smacky™",
			"url": "  ",
			"thumbUrl": "  ",
			"name": "         ",

	"category": "Popular Wallpapers"
		},

		{
			"author": "Smacky™",
			"url": "  ",
			"thumbUrl": "  ",
			"name": "         ",

	"category": "Popular Wallpapers"
		},
















		{
			"author": "Smacky™",
			"url": "  ",
			"thumbUrl": "  ",
			"name": "         ",

	"category": "Quotes"
		},
		{
			"author": "Smacky™",
			"url": "  ",
			"thumbUrl": "  ",
			"name": "         ",

	"category": "Quotes"
		},
		{
			"author": "Smacky™",
			"url": "  ",
			"thumbUrl": "  ",
			"name": "         ",

	"category": "Quotes"
		},
		{
			"author": "Smacky™",
			"url": "  ",
			"thumbUrl": "  ",
			"name": "         ",

	"category": "Quotes"
		},
		{
			"author": "Smacky™",
			"url": "  ",
			"thumbUrl": "  ",
			"name": "         ",

	"category": "Quotes"
		},
		{
			"author": "Smacky™",
			"url": "  ",
			"thumbUrl": "  ",
			"name": "         ",

	"category": "Quotes"
		},
		{
			"author": "Smacky™",
			"url": "  ",
			"thumbUrl": "  ",
			"name": "         ",

	"category": "Quotes"
		},
		{
			"author": "Smacky™",
			"url": "  ",
			"thumbUrl": "  ",
			"name": "         ",

	"category": "Quotes"
		},
		{
			"author": "Smacky™",
			"url": "  ",
			"thumbUrl": "  ",
			"name": "         ",

	"category": "Quotes"
		},
		{
			"author": "Smacky™",
			"url": "  ",
			"thumbUrl": "  ",
			"name": "         ",

	"category": "Quotes"
		},
		{
			"author": "Smacky™",
			"url": "  ",
			"thumbUrl": "  ",
			"name": "         ",

	"category": "Quotes"
		},
		{
			"author": "Smacky™",
			"url": "  ",
			"thumbUrl": "  ",
			"name": "         ",

	"category": "Quotes"
		},
		{
			"author": "Smacky™",
			"url": "  ",
			"thumbUrl": "  ",
			"name": "         ",

	"category": "Quotes"
		},
		{
			"author": "Smacky™",
			"url": "  ",
			"thumbUrl": "  ",
			"name": "         ",

	"category": "Quotes"
		},
		{
			"author": "Smacky™",
			"url": "  ",
			"thumbUrl": "  ",
			"name": "         ",

	"category": "Quotes"
		},
		{
			"author": "Smacky™",
			"url": "  ",
			"thumbUrl": "  ",
			"name": "         ",

	"category": "Quotes"
		},
		{
			"author": "Smacky™",
			"url": "  ",
			"thumbUrl": "  ",
			"name": "         ",

	"category": "Quotes"
		},
		{
			"author": "Smacky™",
			"url": "  ",
			"thumbUrl": "  ",
			"name": "         ",

	"category": "Quotes"
		},
		{
			"author": "Smacky™",
			"url": "  ",
			"thumbUrl": "  ",
			"name": "         ",

	"category": "Quotes"
		},
		{
			"author": "Smacky™",
			"url": "  ",
			"thumbUrl": "  ",
			"name": "         ",

	"category": "Quotes"
		},
		{
			"author": "Smacky™",
			"url": "  ",
			"thumbUrl": "  ",
			"name": "         ",

	"category": "Quotes"
		},
		{
			"author": "Smacky™",
			"url": "  ",
			"thumbUrl": "  ",
			"name": "         ",

	"category": "Quotes"
		},
		{
			"author": "Smacky™",
			"url": "  ",
			"thumbUrl": "  ",
			"name": "         ",

	"category": "Quotes"
		},
		{
			"author": "Smacky™",
			"url": "  ",
			"thumbUrl": "  ",
			"name": "         ",

	"category": "Quotes"
		},
		{
			"author": "Smacky™",
			"url": "  ",
			"thumbUrl": "  ",
			"name": "         ",

	"category": "Quotes"
		},
		{
			"author": "Smacky™",
			"url": "  ",
			"thumbUrl": "  ",
			"name": "         ",

	"category": "Quotes"
		},
		{
			"author": "Smacky™",
			"url": "  ",
			"thumbUrl": "  ",
			"name": "         ",

	"category": "Quotes"
		},
		{
			"author": "Smacky™",
			"url": "  ",
			"thumbUrl": "  ",
			"name": "         ",

	"category": "Quotes"
		},
		{
			"author": "Smacky™",
			"url": "  ",
			"thumbUrl": "  ",
			"name": "         ",

	"category": "Quotes"
		},
		{
			"author": "Smacky™",
			"url": "  ",
			"thumbUrl": "  ",
			"name": "         ",

	"category": "Quotes"
		},
		{
			"author": "Smacky™",
			"url": "  ",
			"thumbUrl": "  ",
			"name": "         ",

	"category": "Quotes"
		},
		{
			"author": "Smacky™",
			"url": "  ",
			"thumbUrl": "  ",
			"name": "         ",

	"category": "Quotes"
		},












		{
			"author": "Smacky™",
			"url": "  ",
			"thumbUrl": "  ",
			"name": "         ",

	"category": "Roads"
		},
		{
			"author": "Smacky™",
			"url": "  ",
			"thumbUrl": "  ",
			"name": "         ",

	"category": "Roads"
		},
		{
			"author": "Smacky™",
			"url": "  ",
			"thumbUrl": "  ",
			"name": "         ",

	"category": "Roads"
		},
		{
			"author": "Smacky™",
			"url": "  ",
			"thumbUrl": "  ",
			"name": "         ",

	"category": "Roads"
		},
		{
			"author": "Smacky™",
			"url": "  ",
			"thumbUrl": "  ",
			"name": "         ",

	"category": "Roads"
		},
		{
			"author": "Smacky™",
			"url": "  ",
			"thumbUrl": "  ",
			"name": "         ",

	"category": "Roads"
		},
		{
			"author": "Smacky™",
			"url": "  ",
			"thumbUrl": "  ",
			"name": "         ",

	"category": "Roads"
		},
		{
			"author": "Smacky™",
			"url": "  ",
			"thumbUrl": "  ",
			"name": "         ",

	"category": "Roads"
		},
		{
			"author": "Smacky™",
			"url": "  ",
			"thumbUrl": "  ",
			"name": "         ",

	"category": "Roads"
		},
		{
			"author": "Smacky™",
			"url": "  ",
			"thumbUrl": "  ",
			"name": "         ",

	"category": "Roads"
		},











		{
			"author": "Smacky™",
			"url": "  ",
			"thumbUrl": "  ",
			"name": "         ",

	"category": "Sky"
		},
		{
			"author": "Smacky™",
			"url": "  ",
			"thumbUrl": "  ",
			"name": "         ",

	"category": "Sky"
		},
		{
			"author": "Smacky™",
			"url": "  ",
			"thumbUrl": "  ",
			"name": "         ",

	"category": "Sky"
		},
		{
			"author": "Smacky™",
			"url": "  ",
			"thumbUrl": "  ",
			"name": "         ",

	"category": "Sky"
		},
		{
			"author": "Smacky™",
			"url": "  ",
			"thumbUrl": "  ",
			"name": "         ",

	"category": "Sky"
		},
		{
			"author": "Smacky™",
			"url": "  ",
			"thumbUrl": "  ",
			"name": "         ",

	"category": "Sky"
		},
		{
			"author": "Smacky™",
			"url": "  ",
			"thumbUrl": "  ",
			"name": "         ",

	"category": "Sky"
		},
		{
			"author": "Smacky™",
			"url": "  ",
			"thumbUrl": "  ",
			"name": "         ",

	"category": "Sky"
		},
		{
			"author": "Smacky™",
			"url": "  ",
			"thumbUrl": "  ",
			"name": "         ",

	"category": "Sky"
		},
		{
			"author": "Smacky™",
			"url": "  ",
			"thumbUrl": "  ",
			"name": "         ",

	"category": "Sky"
		},
		{
			"author": "Smacky™",
			"url": "  ",
			"thumbUrl": "  ",
			"name": "         ",

	"category": "Sky"
		},
		{
			"author": "Smacky™",
			"url": "  ",
			"thumbUrl": "  ",
			"name": "         ",

	"category": "Sky"
		},
		{
			"author": "Smacky™",
			"url": "  ",
			"thumbUrl": "  ",
			"name": "         ",

	"category": "Sky"
		},
		{
			"author": "Smacky™",
			"url": "  ",
			"thumbUrl": "  ",
			"name": "         ",

	"category": "Sky"
		},














		{
			"author": "Smacky™",
			"url": "  ",
			"thumbUrl": "  ",
			"name": "         ",

	"category": "Textures"
		},
		{
			"author": "Smacky™",
			"url": "  ",
			"thumbUrl": "  ",
			"name": "         ",

	"category": "Textures"
		},
		{
			"author": "Smacky™",
			"url": "  ",
			"thumbUrl": "  ",
			"name": "         ",

	"category": "Textures"
		},
		{
			"author": "Smacky™",
			"url": "  ",
			"thumbUrl": "  ",
			"name": "         ",

	"category": "Textures"
		},
		{
			"author": "Smacky™",
			"url": "  ",
			"thumbUrl": "  ",
			"name": "         ",

	"category": "Textures"
		},
		{
			"author": "Smacky™",
			"url": "  ",
			"thumbUrl": "  ",
			"name": "         ",

	"category": "Textures"
		},
		{
			"author": "Smacky™",
			"url": "  ",
			"thumbUrl": "  ",
			"name": "         ",

	"category": "Textures"
		},
		{
			"author": "Smacky™",
			"url": "  ",
			"thumbUrl": "  ",
			"name": "         ",

	"category": "Textures"
		},
		{
			"author": "Smacky™",
			"url": "  ",
			"thumbUrl": "  ",
			"name": "         ",

	"category": "Textures"
		},
		{
			"author": "Smacky™",
			"url": "  ",
			"thumbUrl": "  ",
			"name": "         ",

	"category": "Textures"
		},
		{
			"author": "Smacky™",
			"url": "  ",
			"thumbUrl": "  ",
			"name": "         ",

	"category": "Textures"
		},
		{
			"author": "Smacky™",
			"url": "  ",
			"thumbUrl": "  ",
			"name": "         ",

	"category": "Textures"
		},
		{
			"author": "Smacky™",
			"url": "  ",
			"thumbUrl": "  ",
			"name": "         ",

	"category": "Textures"
		},
		{
			"author": "Smacky™",
			"url": "  ",
			"thumbUrl": "  ",
			"name": "         ",

	"category": "Textures"
		},
		{
			"author": "Smacky™",
			"url": "  ",
			"thumbUrl": "  ",
			"name": "         ",

	"category": "Textures"
		},
		{
			"author": "Smacky™",
			"url": "  ",
			"thumbUrl": "  ",
			"name": "         ",

	"category": "Textures"
		},
		{
			"author": "Smacky™",
			"url": "  ",
			"thumbUrl": "  ",
			"name": "         ",

	"category": "Textures"
		},
		{
			"author": "Smacky™",
			"url": "  ",
			"thumbUrl": "  ",
			"name": "         ",

	"category": "Textures"
		},
		{
			"author": "Smacky™",
			"url": "  ",
			"thumbUrl": "  ",
			"name": "         ",

	"category": "Textures"
		},
		{
			"author": "Smacky™",
			"url": "  ",
			"thumbUrl": "  ",
			"name": "         ",

	"category": "Textures"
		},
		{
			"author": "Smacky™",
			"url": "  ",
			"thumbUrl": "  ",
			"name": "         ",

	"category": "Textures"
		},
		{
			"author": "Smacky™",
			"url": "  ",
			"thumbUrl": "  ",
			"name": "         ",

	"category": "Textures"
		},
		{
			"author": "Smacky™",
			"url": "  ",
			"thumbUrl": "  ",
			"name": "         ",

	"category": "Textures"
		},
		{
			"author": "Smacky™",
			"url": "  ",
			"thumbUrl": "  ",
			"name": "         ",

	"category": "Textures"
		},
		{
			"author": "Smacky™",
			"url": "  ",
			"thumbUrl": "  ",
			"name": "         ",

	"category": "Textures"
		},
		{
			"author": "Smacky™",
			"url": "  ",
			"thumbUrl": "  ",
			"name": "         ",

	"category": "Textures"
		},
		{
			"author": "Smacky™",
			"url": "  ",
			"thumbUrl": "  ",
			"name": "         ",

	"category": "Textures"
		},
		{
			"author": "Smacky™",
			"url": "  ",
			"thumbUrl": "  ",
			"name": "         ",

	"category": "Textures"
		},
		{
			"author": "Smacky™",
			"url": "  ",
			"thumbUrl": "  ",
			"name": "         ",

	"category": "Textures"
		},
		{
			"author": "Smacky™",
			"url": "  ",
			"thumbUrl": "  ",
			"name": "         ",

	"category": "Textures"
		},
		{
			"author": "Smacky™",
			"url": "  ",
			"thumbUrl": "  ",
			"name": "         ",

	"category": "Textures"
		},
		{
			"author": "Smacky™",
			"url": "  ",
			"thumbUrl": "  ",
			"name": "         ",

	"category": "Textures"
		},
		{
			"author": "Smacky™",
			"url": "  ",
			"thumbUrl": "  ",
			"name": "         ",

	"category": "Textures"
		},
		{
			"author": "Smacky™",
			"url": "  ",
			"thumbUrl": "  ",
			"name": "         ",

	"category": "Textures"
		},
		{
			"author": "Smacky™",
			"url": "  ",
			"thumbUrl": "  ",
			"name": "         ",

	"category": "Textures"
		},
		{
			"author": "Smacky™",
			"url": "  ",
			"thumbUrl": "  ",
			"name": "         ",

	"category": "Textures"
		},
		{
			"author": "Smacky™",
			"url": "  ",
			"thumbUrl": "  ",
			"name": "         ",

	"category": "Textures"
		},
		{
			"author": "Smacky™",
			"url": "  ",
			"thumbUrl": "  ",
			"name": "         ",

	"category": "Textures"
		},
		{
			"author": "Smacky™",
			"url": "  ",
			"thumbUrl": "  ",
			"name": "         ",

	"category": "Textures"
		},
		{
			"author": "Smacky™",
			"url": "  ",
			"thumbUrl": "  ",
			"name": "         ",

	"category": "Textures"
		},
		{
			"author": "Smacky™",
			"url": "  ",
			"thumbUrl": "  ",
			"name": "         ",

	"category": "Textures"
		},















		{
			"author": "Smacky™",
			"url": "  ",
			"thumbUrl": "  ",
			"name": "         ",

	"category": "Ultrawide Wallpapers"
		},
		{
			"author": "Smacky™",
			"url": "  ",
			"thumbUrl": "  ",
			"name": "         ",

	"category": "Ultrawide Wallpapers"
		},
		{
			"author": "Smacky™",
			"url": "  ",
			"thumbUrl": "  ",
			"name": "         ",

	"category": "Ultrawide Wallpapers"
		},
		{
			"author": "Smacky™",
			"url": "  ",
			"thumbUrl": "  ",
			"name": "         ",

	"category": "Ultrawide Wallpapers"
		},
		{
			"author": "Smacky™",
			"url": "  ",
			"thumbUrl": "  ",
			"name": "         ",

	"category": "Ultrawide Wallpapers"
		},
		{
			"author": "Smacky™",
			"url": "  ",
			"thumbUrl": "  ",
			"name": "         ",

	"category": "Ultrawide Wallpapers"
		},
		{
			"author": "Smacky™",
			"url": "  ",
			"thumbUrl": "  ",
			"name": "         ",

	"category": "Ultrawide Wallpapers"
		},
		{
			"author": "Smacky™",
			"url": "  ",
			"thumbUrl": "  ",
			"name": "         ",

	"category": "Ultrawide Wallpapers"
		},
		{
			"author": "Smacky™",
			"url": "  ",
			"thumbUrl": "  ",
			"name": "         ",

	"category": "Ultrawide Wallpapers"
		},
		{
			"author": "Smacky™",
			"url": "  ",
			"thumbUrl": "  ",
			"name": "         ",

	"category": "Ultrawide Wallpapers"
		},
		{
			"author": "Smacky™",
			"url": "  ",
			"thumbUrl": "  ",
			"name": "         ",

	"category": "Ultrawide Wallpapers"
		},
		{
			"author": "Smacky™",
			"url": "  ",
			"thumbUrl": "  ",
			"name": "         ",

	"category": "Ultrawide Wallpapers"
		},
		{
			"author": "Smacky™",
			"url": "  ",
			"thumbUrl": "  ",
			"name": "         ",

	"category": "Ultrawide Wallpapers"
		},
		{
			"author": "Smacky™",
			"url": "  ",
			"thumbUrl": "  ",
			"name": "         ",

	"category": "Ultrawide Wallpapers"
		},
		{
			"author": "Smacky™",
			"url": "  ",
			"thumbUrl": "  ",
			"name": "         ",

	"category": "Ultrawide Wallpapers"
		},
		{
			"author": "Smacky™",
			"url": "  ",
			"thumbUrl": "  ",
			"name": "         ",

	"category": "Ultrawide Wallpapers"
		},
		{
			"author": "Smacky™",
			"url": "  ",
			"thumbUrl": "  ",
			"name": "         ",

	"category": "Ultrawide Wallpapers"
		},
		{
			"author": "Smacky™",
			"url": "  ",
			"thumbUrl": "  ",
			"name": "         ",

	"category": "Ultrawide Wallpapers"
		},
		{
			"author": "Smacky™",
			"url": "  ",
			"thumbUrl": "  ",
			"name": "         ",

	"category": "Ultrawide Wallpapers"
		}




	]
}
